Metadata-Version: 2.4
Name: sim-sdk
Version: 0.0.6
Summary: qtest环境
Author: ZhiZi-jack
Requires-Python: >=3.9
Requires-Dist: elasticsearch==7.11.0
Requires-Dist: esdk-obs-python==3.23.12
Requires-Dist: pymysql==1.1.1
Requires-Dist: pyarrow==15.0.2
Requires-Dist: pandas==2.2.1
Requires-Dist: numpy==1.26.4
Requires-Dist: redis==5.0.3
Requires-Dist: minio==7.2.7
Requires-Dist: requests==2.32.0
Requires-Dist: nacos-sdk-python==1.0.0
Requires-Dist: pyyaml==6.0.2
Requires-Dist: protobuf==5.27.3
Requires-Dist: ffmpeg-python==0.2.0
Dynamic: author
Dynamic: requires-dist
Dynamic: requires-python
Dynamic: summary
